scrapy_script.py
scrapy_script-1.0.0.dist-info/LICENCE
scrapy_script-1.0.0.dist-info/METADATA
scrapy_script-1.0.0.dist-info/WHEEL
scrapy_script-1.0.0.dist-info/top_level.txt
scrapy_script-1.0.0.dist-info/RECORD
