Metadata-Version: 2.1
Name: scrapy-script
Version: 1.0.0
Summary: Run a Scrapy spider programmatically from a script or a Celery task - no project required.
Home-page: https://github.com/aox-lei/scrapyscript
Author: Aox lei
Author-email: 2387813033@qq.com
License: MIT
Keywords: scrapy
Platform: UNKNOWN
Classifier: Programming Language :: Python :: 2.7
Classifier: Programming Language :: Python :: 3.4
Classifier: Framework :: Scrapy
Classifier: Intended Audience :: Developers
Classifier: License :: OSI Approved :: MIT License
Requires-Dist: Scrapy (>=1.4.0)
Requires-Dist: billiard (>=3.5.0.2)
